hiconet/HiCoNet.py
hiconet/__init__.py
hiconet/community_detection.py
hiconet/data_society.py
hiconet/export.py
hiconet/html_visual.py
hiconet/input_functions.py
hiconet/pls2_network.py
hiconet/btm/__init__.py
hiconet/btm/btm_example_data.py
hiconet/btm/btm_tool.py
hiconet-0.5.4.data/data/datasets/Colombia/HILIC_pos_diag_basel.txt
hiconet-0.5.4.data/data/datasets/Colombia/HILIC_pos_diag_basel_feature_annotation.txt
hiconet-0.5.4.data/data/datasets/Colombia/formatted_BTMs_diag_basel.txt
hiconet-0.5.4.data/data/datasets/Colombia/project.yaml
hiconet-0.5.4.data/data/datasets/Colombia/samples_meta.txt
hiconet-0.5.4.data/data/datasets/SDY80/BTMactivity_SDY80.txt
hiconet-0.5.4.data/data/datasets/SDY80/SDY80_fcs__data_matrix.txt
hiconet-0.5.4.data/data/datasets/SDY80/SDY80_fcs__observation_annotation.txt
hiconet-0.5.4.data/data/datasets/SDY80/biosample.txt
hiconet-0.5.4.data/data/datasets/SDY80/neut_ab_titer__data_matrix.txt
hiconet-0.5.4.data/data/datasets/SDY80/neut_ab_titer__observation_annotation.txt
hiconet-0.5.4.data/data/datasets/SDY80/project.yaml
hiconet-0.5.4.dist-info/LICENSE
hiconet-0.5.4.dist-info/METADATA
hiconet-0.5.4.dist-info/WHEEL
hiconet-0.5.4.dist-info/top_level.txt
hiconet-0.5.4.dist-info/RECORD
