Metadata-Version: 2.1
Name: hiconet
Version: 0.5.4
Summary: Hierachical Community Network, data driven omics integration
Home-page: https://github.com/shuzhao-li/hiconet
Author: Shuzhao Li
Author-email: shuzhao.li@gmail.com
License: BSD
Keywords: bioinformatics systems biology immunology
Classifier: Development Status :: 4 - Beta
Classifier: Intended Audience :: Developers
Classifier: Intended Audience :: Science/Research
Classifier: License :: OSI Approved :: BSD License
Classifier: Natural Language :: English
Classifier: Operating System :: OS Independent
Classifier: Programming Language :: Python :: 3.7
Classifier: Topic :: Scientific/Engineering :: Bio-Informatics
Classifier: Topic :: Software Development :: Libraries :: Python Modules
Requires-Python: >=3
License-File: LICENSE
Requires-Dist: numpy
Requires-Dist: scipy
Requires-Dist: pandas
Requires-Dist: sklearn
Requires-Dist: leidenalg
Requires-Dist: python-igraph
Requires-Dist: fuzzywuzzy
Requires-Dist: pyyaml
Requires-Dist: scanpy
